whyis_weaviate/__init__.py
whyis_weaviate/_version.py
whyis_weaviate/plugin.py
whyis_weaviate/entity_linker/__init__.py
whyis_weaviate/entity_linker/entity_linker.py
whyis_weaviate/templates/resource_get.json
whyis_weaviate/templates/resource_search.json
whyis_weaviate/templates/space_get.json
whyis_weaviate/templates/space_search.json
whyis_weaviate-0.2.0.dist-info/LICENSE
whyis_weaviate-0.2.0.dist-info/METADATA
whyis_weaviate-0.2.0.dist-info/WHEEL
whyis_weaviate-0.2.0.dist-info/entry_points.txt
whyis_weaviate-0.2.0.dist-info/top_level.txt
whyis_weaviate-0.2.0.dist-info/RECORD
